LICENCE.txt
MANIFEST.in
README.md
requirements-2.txt
requirements-3.txt
requirements.txt
setup.py
rabix/__init__.py
rabix/conformance.py
rabix/executor.py
rabix/main.py
rabix/workflows.py
rabix.egg-info/PKG-INFO
rabix.egg-info/SOURCES.txt
rabix.egg-info/dependency_links.txt
rabix.egg-info/entry_points.txt
rabix.egg-info/not-zip-safe
rabix.egg-info/requires.txt
rabix.egg-info/top_level.txt
rabix/cli/__init__.py
rabix/cli/adapter.py
rabix/cli/cli_app.py
rabix/common/__init__.py
rabix/common/context.py
rabix/common/errors.py
rabix/common/io.py
rabix/common/models.py
rabix/common/ref_resolver.py
rabix/common/util.py
rabix/common/validations.py
rabix/docker/__init__.py
rabix/docker/container.py
rabix/docker/docker_app.py
rabix/expressions/__init__.py
rabix/expressions/evaluator.py
rabix/expressions/expression_tool.py
rabix/tests/__init__.py
rabix/tests/integration_test.py
rabix/tests/test_build.py
rabix/tests/test_schema.py
rabix/tests/test_cli/__init__.py
rabix/tests/test_cli/test_adapter.py
rabix/tests/test_cli/test_cli.py
rabix/tests/test_common/__init__.py
rabix/tests/test_common/test_io.py
rabix/tests/test_common/test_model.py
rabix/tests/test_common/test_util.py
rabix/tests/test_docker/__init__.py
rabix/tests/test_docker/test_docker_container.py
rabix/tests/test_executors/__init__.py
rabix/tests/test_executors/test_cli.py
rabix/tests/test_executors/test_runners.py
rabix/tools/__init__.py
rabix/tools/build.py
rabix/tools/cli.py